django_elastipymemcache/__init__.py
django_elastipymemcache/backend.py
django_elastipymemcache/client.py
django_elastipymemcache-2.0.5.dist-info/LICENSE
django_elastipymemcache-2.0.5.dist-info/METADATA
django_elastipymemcache-2.0.5.dist-info/WHEEL
django_elastipymemcache-2.0.5.dist-info/top_level.txt
django_elastipymemcache-2.0.5.dist-info/RECORD
