Metadata-Version: 2.1
Name: django-elastipymemcache
Version: 2.0.5
Summary: Django cache backend for Amazon ElastiCache (memcached)
Home-page: http://github.com/harikitech/django-elastipymemcache
Author: HarikiTech
Author-email: harikitech+noreply@googlegroups.com
License: MIT
Keywords: elasticache amazon cache pymemcache memcached aws
Platform: any
Classifier: Development Status :: 4 - Beta
Classifier: Environment :: Web Environment
Classifier: Framework :: Django :: 2.2
Classifier: Framework :: Django :: 3.0
Classifier: Framework :: Django :: 3.1
Classifier: Intended Audience :: Developers
Classifier: License :: OSI Approved :: MIT License
Classifier: Operating System :: OS Independent
Classifier: Programming Language :: Python :: 3.6
Classifier: Programming Language :: Python :: 3.7
Classifier: Programming Language :: Python :: 3.8
Classifier: Topic :: Software Development :: Libraries :: Python Modules
License-File: LICENSE
Requires-Dist: django-pymemcache>=1.0
Requires-Dist: Django>=2.2
